{
  "Jimmy": {
    "trend_analysis": "本周整体健康状态呈现'两端高、中间波动'的特征。周一到周五期间，您的心率变异性（HRV）维持在54.6-62.9ms的健康区间，静息心率保持在57-61bpm的优秀水平，显示自主神经系统运行良好。特别值得注意的是周五（2月27日）达到了本周HRV峰值62.9ms，表明身体恢复状态极佳。然而周六（2月28日）出现明显异常：HRV骤降至38.2ms（较周均值下降31%），静息心率升高至63bpm，同时步数激增至13016步、爬楼26层，睡眠中清醒时间长达1.34小时（是其他日期的6-10倍）。这组数据强烈提示周六经历了高强度体力活动或外出奔波，导致身体负荷过载，自主神经平衡被暂时打破。好在周日HRV迅速恢复至60.0ms，显示身体自我调节能力良好。\n\n**各项指标的周平均值分析**：心率变异性（HRV）周均值55.43ms，对于22岁男性属于中等偏上水平，正常范围通常在50-100ms，您的数值反映较好的心脏自主调节能力，但周六的骤降提示需要关注过度活动后的恢复。静息心率周均值59.43bpm，非常优秀，运动员级水平（<60bpm），显示心血管健康状况良好。步数日均4751步，低于推荐的8000-10000步健康目标，其中周六贡献了近30%的周总量，说明日常活动量偏少，存在'久坐+突发高强度'的不健康模式。睡眠平均8.24小时总时长看似充足，但结构不均衡——深度睡眠仅1.01小时（正常成人需要1.5-2小时），REM睡眠1.86小时接近正常下限。睡眠质量评分中等，周六睡眠碎片化严重（清醒1.34小时）是主要拉分项。血氧饱和度均值96.2%，正常健康范围。活动热量日均303kcal，中等偏低，建议提升至400-500kcal以维持代谢健康。\n\n**与上周对比分析**：由于缺少上周完整数据，基于本周内部对比分析：工作日（周一至周五）与周末呈现截然不同的健康画像。工作日HRV均值57.8ms、睡眠8.76小时，周末HRV均值49.1ms、睡眠7.48小时。周末虽然活动量增加（日均7779步 vs 工作日2900步），但睡眠质量下降明显，尤其周六的睡眠效率降低。这提示'周末补眠'策略效果有限，睡眠债无法通过单日长睡完全弥补。",
    "recommendations": [
      {
        "title": "🌙 优化睡眠结构",
        "content": "深度睡眠不足是本周最大短板。建议：1）固定作息时间，即使周末也保持相近的睡眠窗口；2）睡前1小时避免剧烈运动（周六的高活动量可能是影响睡眠的主因）；3）尝试睡前冥想或深呼吸练习提升深度睡眠比例。目标将深度睡眠从1.01小时提升至1.3小时以上。"
      },
      {
        "title": "🚶 均衡活动分布",
        "content": "改变'久坐一周+突然暴走'的模式，将周六的高强度活动分散到每周3-4天。建议设置每日步数目标8000步，工作日每坐1小时起身活动5分钟。这样既能保持代谢活跃，又能避免单日的过度疲劳对身体造成冲击。"
      },
      {
        "title": "💓 关注HRV恢复",
        "content": "周六HRV骤降后次日即恢复，说明身体韧性较好，但仍需避免频繁的高负荷冲击。建议在高强度活动日增加主动恢复措施：充足补水、营养补充、晚间拉伸放松。下周重点关注HRV是否稳定在55ms以上，如再次出现骤降需适当降低活动强度。"
      },
      {
        "title": "🥗 营养与水分补充",
        "content": "高强度活动日（如周六）注意补充电解质和优质蛋白质，避免脱水导致的HRV波动和睡眠质量下降。建议在长时间活动后30分钟内补充碳水化合物+蛋白质（如香蕉+酸奶），促进身体恢复。"
      },
      {
        "title": "📊 下周监测重点",
        "content": "下周重点关注：1）深度睡眠时长能否突破1.3小时；2）HRV均值能否稳定在55-60ms区间；3）步数分布是否更加均衡；4）周末睡眠质量是否有改善。建议每天固定时间查看健康数据，建立健康意识。"
      }
    ],
    "key_findings": [
      "HRV周均值55.43ms，周六异常下降至38.2ms后迅速恢复",
      "静息心率保持优秀水平（59.43bpm），心血管健康良好",
      "步数日均4751步偏低，呈现'久坐+突发高强度'模式",
      "睡眠总时长8.24小时充足，但深度睡眠1.01小时不足",
      "周六活动量过大（13016步+26层爬楼）导致睡眠质量显著下降"
    ]
  }
}
